CHANGES.txt
LICENSE.txt
MANIFEST.in
README.rst
pyproject.toml
requirements-dev.txt
requirements.txt
setup.cfg
docs/license.txt
tests/test_wsdl.py
tests/test_wstools_net.py
wstools/MIMEAttachment.py
wstools/Namespaces.py
wstools/TimeoutSocket.py
wstools/UserTuple.py
wstools/Utility.py
wstools/WSDLTools.py
wstools/XMLSchema.py
wstools/XMLname.py
wstools/__init__.py
wstools/c14n.py
wstools/version.py
wstools_py3.egg-info/PKG-INFO
wstools_py3.egg-info/SOURCES.txt
wstools_py3.egg-info/dependency_links.txt
wstools_py3.egg-info/requires.txt
wstools_py3.egg-info/top_level.txt