Metadata-Version: 2.1
Name: wstools-py3
Version: 0.54.5
Summary: WSDL parsing services package for Web Services for Python. seehttps://github.com/Synerty/wstools-py3
Author-email: Makina Corpus <python@makina-corpus.com>
Maintainer-email: Synerty <contact@synerty.com>
License: BSD
Project-URL: Homepage, https://github.com/Synerty/wstools-py3
Keywords: api,wstools,wdsl,web
Classifier: Programming Language :: Python
Classifier: Programming Language :: Python :: 3
Classifier: Development Status :: 5 - Production/Stable
Classifier: Environment :: Other Environment
Classifier: Intended Audience :: Developers
Classifier: License :: OSI Approved :: BSD License
Classifier: Operating System :: OS Independent
Classifier: Topic :: Software Development :: Libraries :: Python Modules
Classifier: Programming Language :: Python :: 3.4
Classifier: Programming Language :: Python :: 3.5
Classifier: Topic :: Internet :: WWW/HTTP
Provides: wstools
Provides-Extra: testing
License-File: LICENSE.txt
